analysis_tools/__init__.py
analysis_tools/common/__init__.py
analysis_tools/common/config.py
analysis_tools/common/env.py
analysis_tools/common/plot_utils.py
analysis_tools/common/timer.py
analysis_tools/common/utils.py
analysis_tools/eda.py
analysis_tools/metrics.py
analysis_tools/modeling.py
analysis_tools/preprocessing.py
analysis_tools/random.py
analysis_tools/utils.py
analysis_tools-0.3.2.dist-info/METADATA
analysis_tools-0.3.2.dist-info/WHEEL
analysis_tools-0.3.2.dist-info/RECORD
