Metadata-Version: 2.1
Name: analysis-tools
Version: 0.3.2
Summary: Analysis tools for Machine learning projects
Author: alchemine
Author-email: djyoon0223+pypi@gmail.com
Requires-Python: >=3.8,<4.0
Classifier: Programming Language :: Python :: 3
Classifier: Programming Language :: Python :: 3.8
Classifier: Programming Language :: Python :: 3.9
Classifier: Programming Language :: Python :: 3.10
Classifier: Programming Language :: Python :: 3.11
Requires-Dist: dask (==2023.5.0)
Requires-Dist: ipython (==8.12.2)
Requires-Dist: joblib (>=1.3.1,<2.0.0)
Requires-Dist: missingno (>=0.5.2,<0.6.0)
Requires-Dist: pandas (>=2.0.3,<3.0.0)
Requires-Dist: scikit-learn (>=1.3.0,<2.0.0)
Requires-Dist: switch (>=1.1.0,<2.0.0)
Requires-Dist: tabulate (>=0.9.0,<0.10.0)
Requires-Dist: tqdm (>=4.65.0,<5.0.0)
